LICENSE
README.md
setup.py
setup_ini.py
dtm_pyapi/__init__.py
dtm_pyapi/app.py
dtm_pyapi/auth.py
dtm_pyapi/utils.py
dtm_pyapi.egg-info/PKG-INFO
dtm_pyapi.egg-info/SOURCES.txt
dtm_pyapi.egg-info/dependency_links.txt
dtm_pyapi.egg-info/requires.txt
dtm_pyapi.egg-info/top_level.txt