Metadata-Version: 2.1
Name: dtm-pyapi
Version: 0.0.12
Summary: Consumindo APIs facilmente com Python
Home-page: https://github.com/kevinnakasaki/pyAPI
Author: Kevin A. Nakasaki
Author-email: kevin.nakasaki@gmail.com
License: MIT
Platform: UNKNOWN
License-File: LICENSE
